README.txt
setup.py
virtualmethod/__init__.py
virtualmethod/core.py
virtualmethod/method_decorator.py
virtualmethod.egg-info/PKG-INFO
virtualmethod.egg-info/SOURCES.txt
virtualmethod.egg-info/dependency_links.txt
virtualmethod.egg-info/top_level.txt