Metadata-Version: 1.0
Name: virtualmethod
Version: 0.0.1
Summary: Decorator to prevent base class methods from being called directly.
Home-page: http://github.com/bgreenlee/virtualmethod
Author: Brad Greenlee
Author-email: brad@footle.org
License: Apache 2.0
Keywords: decorator,virtual method
Platform: UNKNOWN
Classifier: Development Status :: 3 - Alpha
Classifier: Intended Audience :: Developers
Classifier: License :: OSI Approved :: Apache Software License
Classifier: Operating System :: MacOS :: MacOS X
Classifier: Operating System :: POSIX :: Linux
Classifier: Operating System :: Unix
Classifier: Programming Language :: Python
Classifier: Programming Language :: Python :: 2.6
Classifier: Programming Language :: Python :: 2.7
Classifier: Topic :: Software Development :: Libraries :: Python Modules
